{
    "shim": {
        "awebApi": {
            "deps": [
                "jquery"
            ]
        },
        "easyui": {
            "deps": [
                "jquery",
                "jqueryUI"
            ]
        },
        "echarts": {
            "exports": "echarts"
        },
        "fileUpload": {
            "deps": [
                "jquery"
            ]
        },
        "jquery": {
            "exports": "$"
        },
        "jquery.dataTables": {
            "deps": [
                "jquery"
            ]
        },
        "slimScroll": {
            "deps": [
                "jquery"
            ]
        }
    },
    "paths": {
        "awebIndex": "module/index/index",
        "awebFresher": "AWEB/js/aweb.fresher",
        "awebEnvironment": "AWEB/js/aweb.environment",
        "awebApi": "AWEB/js/aweb.api",
        "awebDependence": "AWEB/js/aweb.dependence",
        "component": "component/index.js",
        "component.AIBSTablesV2": "component.AIBSTablesV2/js/component.AIBSTablesV2.js",
        "component.btn": "component.btn/index.js",
        "component.btn.btnGroup": "component.btn.btnGroup/js/component.btn.btnGroup.js",
        "component.btn.dropdownBtn": "component.btn.dropdownBtn/js/component.btn.dropdownBtn.js",
        "component.btn.fileUploadBtn": "component.btn.fileUploadBtn/js/component.btn.fileUploadBtn.js",
        "component.btn.normalBtn": "component.btn.normalBtn/js/component.btn.normalBtn.js",
        "component.dataTables": "component.dataTables/js/component.dataTables.js",
        "component.echarts": "component.echarts/js/component.echarts.js",
        "component.echarts.bar": "component.echarts.bar/js/component.echarts.bar.js",
        "component.echarts.dashboard": "component.echarts.dashboard/js/component.echarts.dashboard.js",
        "component.echarts.line": "component.echarts.line/js/component.echarts.line.js",
        "component.echarts.pie": "component.echarts.pie/js/component.echarts.pie.js",
        "component.form": "component.form/js/component.form.js",
        "component.form.checkbox": "component.form.checkbox/js/component.form.checkbox.js",
        "component.form.checkboxGroup": "component.form.checkboxGroup/js/component.form.checkboxGroup.js",
        "component.form.input": "component.form.input/js/component.form.input.js",
        "component.form.password": "component.form.password/js/component.form.password.js",
        "component.form.radio": "component.form.radio/js/component.form.radio.js",
        "component.form.radioGroup": "component.form.radioGroup/js/component.form.radioGroup.js",
        "component.form.select": "component.form.select/js/component.form.select.js",
        "component.form.textarea": "component.form.textarea/js/component.form.textarea.js",
        "component.formUnionV2": "component.formUnionV2/js/component.formUnionV2.js",
        "component.foundationForm": "component.foundationForm/js/component.foundationForm.js",
        "component.foundationForm.foundationCKEditor": "component.foundationForm.foundationCKEditor/js/component.foundationForm.foundationCKEditor.js",
        "component.foundationForm.foundationCheckboxGroup": "component.foundationForm.foundationCheckboxGroup/js/component.foundationForm.foundationCheckboxGroup.js",
        "component.foundationForm.foundationDateTimePicker": "component.foundationForm.foundationDateTimePicker/js/component.foundationForm.foundationDateTimePicker.js",
        "component.foundationForm.foundationDatepicker": "component.foundationForm.foundationDatepicker/js/component.foundationForm.foundationDatepicker.js",
        "component.foundationForm.foundationDigitInput": "component.foundationForm.foundationDigitInput/js/component.foundationForm.foundationDigitInput.js",
        "component.foundationForm.foundationEditableSelect": "component.foundationForm.foundationEditableSelect/js/component.foundationForm.foundationEditableSelect.js",
        "component.foundationForm.foundationEditableSilder": "component.foundationForm.foundationEditableSilder/js/component.foundationForm.foundationEditableSilder.js",
        "component.foundationForm.foundationImg": "component.foundationForm.foundationImg/js/component.foundationForm.foundationImg.js",
        "component.foundationForm.foundationInput": "component.foundationForm.foundationInput/js/component.foundationForm.foundationInput.js",
        "component.foundationForm.foundationMultiplePicUpload": "component.foundationForm.foundationMultiplePicUpload/js/component.foundationForm.foundationMultiplePicUpload.js",
        "component.foundationForm.foundationPassword": "component.foundationForm.foundationPassword/js/component.foundationForm.foundationPassword.js",
        "component.foundationForm.foundationRadioGroup": "component.foundationForm.foundationRadioGroup/js/component.foundationForm.foundationRadioGroup.js",
        "component.foundationForm.foundationSelect": "component.foundationForm.foundationSelect/js/component.foundationForm.foundationSelect.js",
        "component.foundationForm.foundationSelectIcon": "component.foundationForm.foundationSelectIcon/js/component.foundationForm.foundationSelectIcon.js",
        "component.foundationForm.foundationSingleUpload": "component.foundationForm.foundationSingleUpload/js/component.foundationForm.foundationSingleUpload.js",
        "component.foundationForm.foundationSwitch": "component.foundationForm.foundationSwitch/js/component.foundationForm.foundationSwitch.js",
        "component.foundationForm.foundationText": "component.foundationForm.foundationText/js/component.foundationForm.foundationText.js",
        "component.foundationForm.foundationTextArea": "component.foundationForm.foundationTextArea/js/component.foundationForm.foundationTextArea.js",
        "component.foundationForm.foundationTreeSelect": "component.foundationForm.foundationTreeSelect/js/component.foundationForm.foundationTreeSelect.js",
        "component.foundationForm.foundationUploadButton": "component.foundationForm.foundationUploadButton/js/component.foundationForm.foundationUploadButton.js",
        "component.foundationForm.foundationVerifyInput": "component.foundationForm.foundationVerifyInput/js/component.foundationForm.foundationVerifyInput.js",
        "component.foundationForm.foundationWangEditor": "component.foundationForm.foundationWangEditor/js/component.foundationForm.foundationWangEditor.js",
        "component.foundationForm.foundationWysiwyg": "component.foundationForm.foundationWysiwyg/js/component.foundationForm.foundationWysiwyg.js",
        "component.handsontable": "component.handsontable/js/component.handsontable.js",
        "component.htmlTag": "component.htmlTag/js/component.htmlTag.js",
        "component.icon": "component.icon/js/component.icon.js",
        "component.img": "component.img/js/component.img.js",
        "component.leftCatalog": "component.leftCatalog/js/component.leftCatalog.js",
        "component.multiHansonTable": "component.multiHansonTable/js/component.multiHansonTable.js",
        "component.other": "component.other/js/component.other.js",
        "component.other.editableDataTable": "component.other.editableDataTable/js/component.other.editableDataTable.js",
        "component.other.horizontalSplitLine": "component.other.horizontalSplitLine/js/component.other.horizontalSplitLine.js",
        "component.other.multipleChoiceListBox": "component.other.multipleChoiceListBox/js/component.other.multipleChoiceListBox.js",
        "component.other.progressBar": "component.other.progressBar/js/component.other.progressBar.js",
        "component.other.timeLine": "component.other.timeLine/js/component.other.timeLine.js",
        "component.other.topology": "component.other.topology/js/component.other.topology.js",
        "component.other.verticalSplitLine": "component.other.verticalSplitLine/js/component.other.verticalSplitLine.js",
        "component.platformEditor": "component.platformEditor/js/component.platformEditor.js",
        "component.platformSplitBar": "component.platformSplitBar/js/component.platformSplitBar.js",
        "component.text": "component.text/js/component.text.js",
        "component.topNav": "component.topNav/js/component.topNav.js",
        "component.zTree": "component.zTree/js/component.zTree.js",
        "ctn": "ctn/js/ctn.js",
        "ctn.divCtn": "ctn.divCtn/js/ctn.divCtn.js",
        "ctn.formCtn": "ctn.formCtn/js/ctn.formCtn.js",
        "ctn.foundationFormCtn": "ctn.foundationFormCtn/js/ctn.foundationFormCtn.js",
        "ctn.foundationRowCtn": "ctn.foundationRowCtn/js/ctn.foundationRowCtn.js",
        "ctn.loginCtn": "ctn.loginCtn/js/ctn.loginCtn.js",
        "ctn.modalCtn": "ctn.modalCtn/js/ctn.modalCtn.js",
        "layout.rowCtn": "layout.rowCtn/js/layout.rowCtn.js",
        "layout.stepCtn": "layout.stepCtn/js/layout.stepCtn.js",
        "layout.tabCtn": "layout.tabCtn/js/layout.tabCtn.js",
        "page.mainPanel": "page.mainPanel/index.js",
        "Handsontable": "Handsontable/js/handsontable.full.min",
        "MultiplePicUpload": "MultiplePicUpload/index.js",
        "bootstrap-switch": "bootstrap-switch/js/bootstrap-switch",
        "bootstrap-wysiwyg": "bootstrap-wysiwyg/js/bootstrap-wysiwyg.js",
        "bootstrap_datepicker": "bootstrap_datepicker/js/bootstrap-datepicker.min",
        "chosen.jquery": "chosen.jquery/js/chosen.jquery",
        "ckEditor": "ckEditor/js/ckeditor",
        "dataTables.buttons.min": "dataTables.buttons.min/js/dataTables.buttons.min",
        "dataTables.editor.min": "dataTables.editor.min/js/dataTables.editor.min",
        "dataTables.fixedColumns.min": "dataTables.fixedColumns.min/js/dataTables.fixedColumns.min",
        "dataTables.select.min": "dataTables.select.min/js/dataTables.select.min",
        "easyui": "easyui/js/jquery.easyui.min",
        "echarts": "echarts/js/echarts.min",
        "editableSilder": "editableSilder/index.js",
        "fileUpload": "fileUpload/js/jQuery.ajaxfileupload.js",
        "fileUploadBtn": "fileUploadBtn/index.js",
        "flatpickr": "flatpickr/js/flatpickr",
        "foundation": "foundation/js/foundation.js",
        "jquery": "jquery/js/jquery-1.9.1.js",
        "jquery.dataTables": "jquery.dataTables/js/jquery.dataTables",
        "jquery.editableSelect": "jquery.editableSelect/js/jquery.editableSelect",
        "jqueryUI": "jqueryUI/js/jquery-ui.min",
        "jtopo.0.4.8.min": "jtopo.0.4.8.min/js/jtopo-0.4.8-min",
        "layout.ctn": "layout.ctn/index.js",
        "leftCatalog": "leftCatalog/index.js",
        "loginCtn": "loginCtn/index.js",
        "moment": "moment/js/moment",
        "multiselect": "multiselect/js/multiselect.js",
        "pikaday": "pikaday/js/pikaday",
        "progressbar": "progressbar/js/progressbar",
        "requireCss": "requireCss/js/require-css.min",
        "requireJS": "requireJS/js/require.js",
        "slimScroll": "slimScroll/js/jquery.slimscroll.min",
        "stepCtn": "stepCtn/index.js",
        "template": "template/js/template",
        "text": "text/js/text",
        "timeLine": "timeLine/index.js",
        "topNav": "topNav/index.js",
        "wangEditor": "wangEditor/js/wangEditor.min",
        "zTree": "zTree/js/jquery.ztree.all-3.5.min"
    },
    "css": [
        "AUI/css/component.btn.css",
        "AWEB/css/aweb.popover.css",
        "AUI/css/component.foundationForm.foundationSelectIcon.css",
        "AUI/css/component.foundationForm.foundationWysiwyg.css",
        "handsonTable/css/handsontable.min.css",
        "MultiplePicUpload/MultiplePicUpload.css",
        "switcher/css/bootstrap-switch.css",
        "bootstrap_datepicker/css/bootstrap-eedatepicker.css",
        "chosen-jquery/css/chosen.css",
        "jQuery.dataTables/css/buttons.dataTables.min.css",
        "jQuery.dataTables/css/editor.dataTables.min.css",
        "jQuery.dataTables/css/fixedColumns.dataTables.css",
        "jQuery.dataTables/css/select.dataTables.min.css",
        "easyui-combotree/easyui.css",
        "editableSilder/css/foundationEditableSilder.css",
        "fileUploadBtn/fileUploadBtn.css",
        "flatpickr/css/flatpickr.css",
        "foundation/css/foundation.css",
        "jQuery.dataTables/css/jquery.dataTables.css",
        "jQuery.ui/jquery-ui.min.css",
        "AUI/css/layout.ctn.css",
        "leftCatalog/leftCatalog.css",
        "leftCatalog/leftCatalogBootstrap.css",
        "loginCtn/loginCtn.css",
        "multiplechoicelistbox/multiplechoicelistbox.css",
        "handsonTable/css/pikaday.css",
        "stepCtn/stepCtn.css",
        "timeLine/css/timeLine.css",
        "topNav/topNav.css",
        "wangEditor/css/wangEditor.min.css",
        "jQuery.zTree/css/awesome.css",
        "AWEB/css/am.css",
        "AWEB/css/aweb.css",
        "AWEB/css/aweb.page.css",
        "AWEB/css/font-awesome.min.css",
        "AWEB/css/icon-font.css",
        "AWEB/css/soy.css"
    ],
    "cssMap": {
        "AUI/css/component.btn.css": "component.btn/css/component.btn.css",
        "AWEB/css/aweb.popover.css": "AWEB/css/aweb.popover.css",
        "AUI/css/component.foundationForm.foundationSelectIcon.css": "component.foundationForm.foundationSelectIcon/css/component.foundationForm.foundationSelectIcon.css",
        "AUI/css/component.foundationForm.foundationWysiwyg.css": "component.foundationForm.foundationWysiwyg/css/component.foundationForm.foundationWysiwyg.css",
        "handsonTable/css/handsontable.min.css": "Handsontable/css/handsontable.min.css",
        "MultiplePicUpload/MultiplePicUpload.css": "MultiplePicUpload/MultiplePicUpload.css",
        "switcher/css/bootstrap-switch.css": "bootstrap-switch/css/bootstrap-switch.css",
        "bootstrap_datepicker/css/bootstrap-eedatepicker.css": "bootstrap_datepicker/css/bootstrap-datepicker.css",
        "chosen-jquery/css/chosen.css": "chosen.jquery/css/chosen.css",
        "jQuery.dataTables/css/buttons.dataTables.min.css": "dataTables.buttons.min/css/buttons.dataTables.min.css",
        "jQuery.dataTables/css/editor.dataTables.min.css": "dataTables.editor.min/css/editor.dataTables.min.css",
        "jQuery.dataTables/css/fixedColumns.dataTables.css": "dataTables.fixedColumns.min/css/fixedColumns.dataTables.css",
        "jQuery.dataTables/css/select.dataTables.min.css": "dataTables.select.min/css/select.dataTables.min.css",
        "easyui-combotree/easyui.css": "easyui/easyui.css",
        "editableSilder/css/foundationEditableSilder.css": "editableSilder/css/foundationEditableSilder.css",
        "fileUploadBtn/fileUploadBtn.css": "fileUploadBtn/css/fileUploadBtn.css",
        "flatpickr/css/flatpickr.css": "flatpickr/css/flatpickr.css",
        "foundation/css/foundation.css": "foundation/css/foundation.css",
        "jQuery.dataTables/css/jquery.dataTables.css": "jquery.dataTables/css/jquery.dataTables.css",
        "jQuery.ui/jquery-ui.min.css": "jqueryUI/css/jquery-ui.min.css",
        "AUI/css/layout.ctn.css": "layout.ctn/css/layout.ctn.css",
        "leftCatalog/leftCatalog.css": "leftCatalog/css/leftCatalog.css",
        "leftCatalog/leftCatalogBootstrap.css": "leftCatalog/css/leftCatalogBootstrap.css",
        "loginCtn/loginCtn.css": "loginCtn/css/loginCtn.css",
        "multiplechoicelistbox/multiplechoicelistbox.css": "multiselect/css/multiplechoicelistbox.css",
        "handsonTable/css/pikaday.css": "pikaday/css/pikaday.css",
        "stepCtn/stepCtn.css": "stepCtn/css/stepCtn.css",
        "timeLine/css/timeLine.css": "timeLine/css/timeLine.css",
        "topNav/topNav.css": "topNav/topNav.css",
        "wangEditor/css/wangEditor.min.css": "wangEditor/css/wangEditor.min.css",
        "jQuery.zTree/css/awesome.css": "zTree/css/awesome.css",
        "AWEB/css/am.css": "AWEB/css/am.css",
        "AWEB/css/aweb.css": "AWEB/css/aweb.css",
        "AWEB/css/aweb.page.css": "AWEB/css/aweb.page.css",
        "AWEB/css/font-awesome.min.css": "AWEB/css/font-awesome.min.css",
        "AWEB/css/icon-font.css": "AWEB/css/icon-font.css",
        "AWEB/css/soy.css": "AWEB/css/soy.css"
    }
}